aiagent_cli/__init__.py
aiagent_cli/analyzer.py
aiagent_cli/auth.py
aiagent_cli/cache.py
aiagent_cli/chunking.py
aiagent_cli/databricks.py
aiagent_cli/generator.py
aiagent_cli/main.py
aiagent_cli/project_brief.py
aiagent_cli/scanner.py
aiagent_2025-0.1.3.dist-info/METADATA
aiagent_2025-0.1.3.dist-info/WHEEL
aiagent_2025-0.1.3.dist-info/entry_points.txt
aiagent_2025-0.1.3.dist-info/licenses/LICENSE
aiagent_2025-0.1.3.dist-info/RECORD
