Metadata-Version: 2.4
Name: aiagent-2025
Version: 0.1.3
Summary: AI-powered CLI agent for codebase analysis and documentation generation using Databricks AI models
Project-URL: Homepage, https://github.com/HossamTabana/aiagent-cli-releases
Project-URL: Repository, https://github.com/HossamTabana/aiagent-cli-releases
Project-URL: Issues, https://github.com/HossamTabana/aiagent-cli-releases/issues
Author: Hossam Tabana
License: MIT
License-File: LICENSE
Keywords: ai,cli,code-analysis,databricks,documentation
Classifier: Development Status :: 3 - Alpha
Classifier: Intended Audience :: Developers
Classifier: License :: OSI Approved :: MIT License
Classifier: Programming Language :: Python :: 3
Classifier: Programming Language :: Python :: 3.11
Classifier: Programming Language :: Python :: 3.12
Classifier: Topic :: Software Development :: Code Generators
Classifier: Topic :: Software Development :: Documentation
Requires-Python: >=3.11
Requires-Dist: click>=8.1.0
Requires-Dist: keyring>=24.0.0
Requires-Dist: openai>=1.0.0
Requires-Dist: pathspec>=0.11.0
Requires-Dist: python-dotenv>=1.0.0
Requires-Dist: pyyaml>=6.0.0
Requires-Dist: rich>=13.0.0
Provides-Extra: dev
Requires-Dist: black>=23.0.0; extra == 'dev'
Requires-Dist: mypy>=1.0.0; extra == 'dev'
Requires-Dist: pytest-cov>=4.0.0; extra == 'dev'
Requires-Dist: pytest>=7.0.0; extra == 'dev'
Requires-Dist: ruff>=0.1.0; extra == 'dev'
